gitrepoxmlparser/__init__.py
gitrepoxmlparser-0.3.0.dist-info/entry_points.txt
gitrepoxmlparser-0.3.0.dist-info/WHEEL
gitrepoxmlparser-0.3.0.dist-info/METADATA
gitrepoxmlparser-0.3.0.dist-info/RECORD
