Metadata-Version: 2.1
Name: gitrepoxmlparser
Version: 0.3.0
Summary: Provides Details for your GitRepo master manifest file 
License: MIT
Author: Ravi Dinesh
Author-email: dineshr93@gmail.com
Requires-Python: >=3.10,<4.0
Classifier: License :: OSI Approved :: MIT License
Classifier: Programming Language :: Python :: 3
Classifier: Programming Language :: Python :: 3.10
Requires-Dist: pywebio (>=1.6.3,<2.0.0)
Requires-Dist: rich (==12.5.1)
